{"value": 158, "indexes": [0, 86, 89]}
{"value": 57, "indexes": [1]}
{"value": 16, "indexes": [2]}
{"value": 131, "indexes": [3, 10]}
{"value": 27, "indexes": [4]}
{"value": 143, "indexes": [5, 51]}
{"value": 116, "indexes": [6]}
{"value": 119, "indexes": [7]}
{"value": 50, "indexes": [8]}
{"value": 102, "indexes": [9]}
{"value": 34, "indexes": [11, 63]}
{"value": 33, "indexes": [12]}
{"value": 29, "indexes": [13]}
{"value": 104, "indexes": [14, 37]}
{"value": 156, "indexes": [15]}
{"value": 55, "indexes": [16]}
{"value": 61, "indexes": [17, 69]}
{"value": 123, "indexes": [18]}
{"value": 38, "indexes": [19]}
{"value": 167, "indexes": [20]}
{"value": 95, "indexes": [21, 33, 87]}
{"value": 12, "indexes": [22]}
{"value": 94, "indexes": [23, 27]}
{"value": 125, "indexes": [24]}
{"value": 41, "indexes": [25, 40]}
{"value": 111, "indexes": [26]}
{"value": 52, "indexes": [28, 71]}
{"value": 68, "indexes": [29, 82]}
{"value": 74, "indexes": [30]}
{"value": 73, "indexes": [31, 84]}
{"value": 115, "indexes": [32, 70]}
{"value": 128, "indexes": [34]}
{"value": 30, "indexes": [35]}
{"value": 117, "indexes": [36, 96]}
{"value": 139, "indexes": [38]}
{"value": 86, "indexes": [39]}
{"value": 113, "indexes": [41]}
{"value": 103, "indexes": [42]}
{"value": 122, "indexes": [43]}
{"value": 101, "indexes": [44, 91]}
{"value": 60, "indexes": [45]}
{"value": 14, "indexes": [46]}
{"value": 112, "indexes": [47]}
{"value": 163, "indexes": [48]}
{"value": 79, "indexes": [49]}
{"value": 81, "indexes": [50]}
{"value": 97, "indexes": [52, 80, 90]}
{"value": 36, "indexes": [53]}
{"value": 59, "indexes": [54, 99]}
{"value": 151, "indexes": [55]}
{"value": 62, "indexes": [56]}
{"value": 32, "indexes": [57]}
{"value": 18, "indexes": [58, 94]}
{"value": 56, "indexes": [59, 85]}
{"value": 149, "indexes": [60]}
{"value": 148, "indexes": [61]}
{"value": 53, "indexes": [62]}
{"value": 154, "indexes": [64, 75]}
{"value": 35, "indexes": [65]}
{"value": 70, "indexes": [66]}
{"value": 77, "indexes": [67]}
{"value": 100, "indexes": [68]}
{"value": 22, "indexes": [72]}
{"value": 114, "indexes": [73]}
{"value": 141, "indexes": [74]}
{"value": 138, "indexes": [76]}
{"value": 39, "indexes": [77]}
{"value": 109, "indexes": [78]}
{"value": 67, "indexes": [79]}
{"value": 124, "indexes": [81]}
{"value": 121, "indexes": [83]}
{"value": 120, "indexes": [88]}
{"value": 130, "indexes": [92]}
{"value": 64, "indexes": [93]}
{"value": 129, "indexes": [95]}
{"value": 54, "indexes": [97]}
{"value": 99, "indexes": [98]}
